MANIFEST.in
README.rst
setup.cfg
setup.py
azure/__init__.py
azure/kusto/__init__.py
azure/kusto/data/__init__.py
azure/kusto/data/_converters.py
azure/kusto/data/_models.py
azure/kusto/data/_version.py
azure/kusto/data/client.py
azure/kusto/data/data_format.py
azure/kusto/data/exceptions.py
azure/kusto/data/helpers.py
azure/kusto/data/response.py
azure/kusto/data/security.py
azure_kusto_data_bot.egg-info/PKG-INFO
azure_kusto_data_bot.egg-info/SOURCES.txt
azure_kusto_data_bot.egg-info/dependency_links.txt
azure_kusto_data_bot.egg-info/requires.txt
azure_kusto_data_bot.egg-info/top_level.txt