Metadata-Version: 2.1
Name: azure-kusto-data-bot
Version: 0.1.1
Summary: Kusto Data Client
Home-page: https://github.com/sshamaiengar/azure-kusto-python-bot
Author: Stephen Shamaiengar
Author-email: s.shamaiengar@gmail.com
License: MIT
Download-URL: https://github.com/sshamaiengar/azure-kusto-python-bot/archive/v0.1.2.tar.gz
Keywords: kusto wrapper client library bot framework
Platform: UNKNOWN
Classifier: Development Status :: 4 - Beta
Classifier: Intended Audience :: Developers
Classifier: Topic :: Software Development
Classifier: Programming Language :: Python :: 3.5
Classifier: Programming Language :: Python :: 3.6
Classifier: Programming Language :: Python :: 3.7
Classifier: Programming Language :: Python :: 3.8
Classifier: License :: OSI Approved :: MIT License
Provides-Extra: pandas
